service_sdk/__init__.py
service_sdk/cli.py
service_sdk/client.py
service_sdk/exceptions.py
service_sdk/manager/controller.py
service_sdk/manager/registry.py
service_sdk/manager/work_manager.py
service_sdk/service.py
service_sdk/utils.py
service_sdk/worker/ex_thread.py
service_sdk/worker/worker.py
dopelemon-0.0.5.dist-info/METADATA
dopelemon-0.0.5.dist-info/WHEEL
dopelemon-0.0.5.dist-info/entry_points.txt
dopelemon-0.0.5.dist-info/RECORD
