Metadata-Version: 2.1
Name: dopelemon
Version: 0.0.5
Summary: Service framework with built-in API
Author: limonyellow
Requires-Python: >=3.8,<4.0
Classifier: Programming Language :: Python :: 3
Classifier: Programming Language :: Python :: 3.8
Classifier: Programming Language :: Python :: 3.9
Classifier: Programming Language :: Python :: 3.10
Classifier: Programming Language :: Python :: 3.11
Classifier: Programming Language :: Python :: 3.12
Requires-Dist: fastapi (>=0.103.1,<0.104.0)
Requires-Dist: pydantic (>=2.3.0,<3.0.0)
Requires-Dist: requests (>=2.31.0,<3.0.0)
Requires-Dist: typer (>=0.9.0,<0.10.0)
Requires-Dist: uvicorn[standard] (>=0.23.2,<0.24.0)
